Workbook
Name aporte: Planilha1!$D$17
Name patrimonio_acumulado: Planilha1!$D$20
Name qtd_anos: Planilha1!$D$18
Name rendimento_carteira: Planilha1!$D$13
Name taxa_mensal: Planilha1!$D$19

Sheet Planilha1
B11: CONFIGURAÇÕES
B12: Salário | D12: 5000
B13: Rendimento Carteira | D13: 0.006
B14: Sugestão de Investimento | D14: =D12*30% -> 1500
B16: INVESTIMENTO MENSAL
B17: Quanto Investir por Mês? | D17: 500
B18: Por Quantos Anos? | D18: 5
B19: Taxa de Rendimento Mensal? | D19: 0.0006
B20: Patrimônio Acumulado? | D20: =FV(rendimento_carteira,qtd_anos*12,aporte*-1) -> 35982.368
B21: Dividendos Mensais? | D21: =patrimonio_acumulado*rendimento_carteira -> 215.89421
B23: Cenários | D23: Dividendo
A24: 2 | B24: Quantos em 2 Anos? | C24: =FV($D$19,A24*12,$D$17*-1) -> 12083.165 | D24: =C24*rendimento_carteira -> 72.498993
A25: 5 | B25: Quantos em 5 Anos? | C25: =FV($D$19,A25*12,$D$17*-1) -> 30537.213 | D25: =C25*rendimento_carteira -> 183.22328
A26: 10 | B26: Quantos em 10 Anos? | C26: =FV($D$19,A26*12,$D$17*-1) -> 62193.451 | D26: =C26*rendimento_carteira -> 373.16071
A27: 20 | B27: Quantos em 20 Anos? | C27: =FV($D$19,A27*12,$D$17*-1) -> 129028.53 | D27: =C27*rendimento_carteira -> 774.17119
A28: 30 | B28: Quantos em 30 Anos? | C28: =FV($D$19,A28*12,$D$17*-1) -> 200851.66 | D28: =C28*rendimento_carteira -> 1205.11
B31: PERFIL | C31: Conservador
B32: VALOR A SER INVESTIDO | C32: =aporte -> 500
B34: TIPO FII | C34: PERCENTUAL SUGERIDO | D34: VALORES
B35: PAPEL | C35: =VLOOKUP($C$31&"-"&B35,Planilha2!A:D,4,0) -> 0.3 | D35: =C35*$C$32 -> 150
B36: TIJOLO | C36: =VLOOKUP($C$31&"-"&B36,Planilha2!A:D,4,0) -> 0.5 | D36: =C36*$C$32 -> 250
B37: HÍBRIDOS | C37: =VLOOKUP($C$31&"-"&B37,Planilha2!A:D,4,0) -> 0.1 | D37: =C37*$C$32 -> 50
B38: FOF's | C38: =VLOOKUP($C$31&"-"&B38,Planilha2!A:D,4,0) -> 0.1 | D38: =C38*$C$32 -> 50
B39: DESENVOLVIMENTO | C39: =VLOOKUP($C$31&"-"&B39,Planilha2!A:D,4,0) -> 0 | D39: =C39*$C$32 -> 0
B40: HOTELARIAS | C40: =VLOOKUP($C$31&"-"&B40,Planilha2!A:D,4,0) -> 0 | D40: =C40*$C$32 -> 0
D41: =SUM(D35:D40) -> 500

Sheet Planilha2
A2: chave | B2: Perfil | C2: TIPO FII | D2: PERCENTUAL SUGERIDO
A3: =B3&"-"&C3 -> Conservador-PAPEL | B3: Conservador | C3: PAPEL | D3: 0.3
A4: =B4&"-"&C4 -> Conservador-TIJOLO | B4: Conservador | C4: TIJOLO | D4: 0.5
A5: =B5&"-"&C5 -> Conservador-HÍBRIDOS | B5: Conservador | C5: HÍBRIDOS | D5: 0.1
A6: =B6&"-"&C6 -> Conservador-FOF's | B6: Conservador | C6: FOF's | D6: 0.1
A7: =B7&"-"&C7 -> Conservador-DESENVOLVIMENTO | B7: Conservador | C7: DESENVOLVIMENTO | D7: 0
A8: =B8&"-"&C8 -> Conservador-HOTELARIAS | B8: Conservador | C8: HOTELARIAS | D8: 0
A9: =B9&"-"&C9 -> Moderado-PAPEL | B9: Moderado | C9: PAPEL | D9: 0.32
A10: =B10&"-"&C10 -> Moderado-TIJOLO | B10: Moderado | C10: TIJOLO | D10: 0.35
A11: =B11&"-"&C11 -> Moderado-HÍBRIDOS | B11: Moderado | C11: HÍBRIDOS | D11: 0.08
A12: =B12&"-"&C12 -> Moderado-FOF's | B12: Moderado | C12: FOF's | D12: 0.05
A13: =B13&"-"&C13 -> Moderado-DESENVOLVIMENTO | B13: Moderado | C13: DESENVOLVIMENTO | D13: 0.1
A14: =B14&"-"&C14 -> Moderado-HOTELARIAS | B14: Moderado | C14: HOTELARIAS | D14: 0.1
... A20: =B20&"-"&C20 -> Agressivo-HOTELARIAS | B20: Agressivo | C20: HOTELARIAS | D20: 0.1
